das_unsupervised/__init__.py
das_unsupervised/event_utils.py
das_unsupervised/spec_utils.py
das_unsupervised-0.6.1.dist-info/LICENSE
das_unsupervised-0.6.1.dist-info/WHEEL
das_unsupervised-0.6.1.dist-info/METADATA
das_unsupervised-0.6.1.dist-info/RECORD
