Metadata-Version: 2.1
Name: das_unsupervised
Version: 0.6.1
Summary: Tools for unsupervised classification of acoustic signals.
Home-page: https://github.com/janclemenslab/das_unsupervised
Author: Jan Clemens
Author-email: clemensjan@googlemail.com
Requires-Python: >=3.6
Classifier: License :: OSI Approved :: MIT License
Requires-Dist: numpy
Requires-Dist: scipy
Requires-Dist: sklearn
Requires-Dist: matplotlib
Requires-Dist: colorcet
Requires-Dist: seaborn
Requires-Dist: librosa
Requires-Dist: noisereduce
Requires-Dist: Pillow
Requires-Dist: umap-learn<0.5
Requires-Dist: hdbscan
